{
  "id": "dmz-peacetrain-2026",
  "name": "DMZ Peace Train Music Festival 2026",
  "startDate": "2026-06-12",
  "endDate": "2026-06-14",
  "location": "강원도 철원 고석정",
  "signatureColor": "forest",
  "status": "upcoming",
  "lineupStage": "stage1_all",
  "description": "DMZ 피스트레인 뮤직 페스티벌은 평화와 공존의 메시지를 음악으로 전하는 국제 음악 축제입니다. 철원 고석정의 자연 속에서 경계를 넘어 음악으로 연결되는 특별한 경험을 선사합니다.",
  "allArtists": [
    "batavia-collective",
    "cha-seungwoo-and-cousins",
    "deadletter",
    "jeon-jayang",
    "fco",
    "funkaphreak",
    "galaxy-express",
    "nourished-by-time",
    "sailor-honeymoon",
    "the-volunteers",
    "thurston-moore",
    "lee-seungyeol",
    "baek-hyeonjin",
    "effie",
    "gymv",
    "in-sooni",
    "la-flemme",
    "lewis-ofman",
    "mildlife",
    "otis-lim",
    "peppertones",
    "peach-truck-hijackers",
    "sinin-ryu",
    "tricot"
  ],
  "lineup": []
}
